{
  "version": "v126_site_to_line_exact_match_speed_fix",
  "website": {
    "cache_version": "126.0",
    "button_text": "產品卡維持「這個適合我嗎？」；全站CTA維持「怎麼選龜鹿？」",
    "site_to_line_text": "我想了解龜鹿膏/龜鹿飲/龜鹿湯塊/龜鹿膠/鹿茸粉適不適合我。",
    "products": 6,
    "faq_count": 60,
    "video_count": 25,
    "missing_local_refs": [],
    "missing_images": [],
    "public_price_hits": [],
    "site_js_syntax": "passed"
  },
  "line_oa": {
    "package_version": "1.2.6",
    "node_check": "passed",
    "missing_images": [],
    "apps_script": "google_apps_script_v126.js",
    "fixes": [
      "新增fastProductIntent精準接住網站按鈕文字",
      "我想了解龜鹿膏適不適合我→直接回龜鹿膏適合度Flex卡",
      "我想了解龜鹿飲適不適合我→直接回龜鹿飲適合度Flex卡",
      "我想了解龜鹿湯塊適不適合我→直接回龜鹿湯塊適合度Flex卡",
      "我想了解龜鹿膠適不適合我→直接回龜鹿膠適合度Flex卡",
      "我想了解鹿茸粉適不適合我→直接回鹿茸粉適合度Flex卡",
      "舊fallback『可以直接點下面按鈕』改成不卡住的Flex選擇卡",
      "follow歡迎訊息改成直接進入怎麼選龜鹿Flex卡",
      "保留原購物車、數量、優惠、付款、Google Sheet功能"
    ],
    "speed_note": "已將網站按鈕文字做前置精準判斷，減少掉入通用判斷；若仍偶爾慢，多半是部署平台冷啟動，可在Render/Railway啟用Always On或定時ping /healthz。"
  }
}