{
  "ok": true,
  "checkedAt": "2026-07-22T12:32:53.133Z",
  "commit": "2c27009f35d1917c5d209fab65ce886e3fb8fbcc",
  "productionUrl": "https://ts-line.onrender.com",
  "lineVersion": "v401.6",
  "productCount": 6,
  "socialVersion": "1.2.1",
  "socialPostCount": 11,
  "internalRuntimeVersion": "20260722-social-6",
  "socialUiVersion": "20260722-social-review-3",
  "socialFormVersion": "20260722-form-stable-3",
  "facebookHealthUiVersion": "20260722-facebook-health-2",
  "socialUiScheduleRule": "週三19:30關心、週五20:00產品、氣候10:00例外加發",
  "instagramConfigured": true,
  "facebookConfigured": true,
  "facebookTokenConfigured": true,
  "facebookTokenUsable": true,
  "facebookTokenExpired": false,
  "facebookTokenSource": "META_PAGE_ACCESS_TOKEN",
  "facebookTokenCheckedAt": "2026-07-22T12:32:52.106Z",
  "facebookTokenError": "",
  "warning": "",
  "internalApp": "仙加味內部管理 App",
  "storage": "supabase"
}
